pybamm/CITATIONS.bib
pybamm/__init__.py
pybamm/_version.py
pybamm/batch_study.py
pybamm/callbacks.py
pybamm/citations.py
pybamm/config.py
pybamm/doc_utils.py
pybamm/logger.py
pybamm/pybamm_data.py
pybamm/settings.py
pybamm/simulation.py
pybamm/telemetry.py
pybamm/type_definitions.py
pybamm/util.py
pybamm/version.py
pybamm/discretisations/__init__.py
pybamm/discretisations/discretisation.py
pybamm/dispatch/__init__.py
pybamm/dispatch/entry_points.py
pybamm/experiment/__init__.py
pybamm/experiment/experiment.py
pybamm/experiment/step/__init__.py
pybamm/experiment/step/base_step.py
pybamm/experiment/step/step_termination.py
pybamm/experiment/step/steps.py
pybamm/expression_tree/__init__.py
pybamm/expression_tree/array.py
pybamm/expression_tree/averages.py
pybamm/expression_tree/binary_operators.py
pybamm/expression_tree/broadcasts.py
pybamm/expression_tree/concatenations.py
pybamm/expression_tree/coupled_variable.py
pybamm/expression_tree/discrete_time_sum.py
pybamm/expression_tree/exceptions.py
pybamm/expression_tree/functions.py
pybamm/expression_tree/independent_variable.py
pybamm/expression_tree/input_parameter.py
pybamm/expression_tree/interpolant.py
pybamm/expression_tree/matrix.py
pybamm/expression_tree/parameter.py
pybamm/expression_tree/scalar.py
pybamm/expression_tree/state_vector.py
pybamm/expression_tree/symbol.py
pybamm/expression_tree/unary_operators.py
pybamm/expression_tree/variable.py
pybamm/expression_tree/vector.py
pybamm/expression_tree/vector_field.py
pybamm/expression_tree/operations/__init__.py
pybamm/expression_tree/operations/convert_to_casadi.py
pybamm/expression_tree/operations/evaluate_python.py
pybamm/expression_tree/operations/jacobian.py
pybamm/expression_tree/operations/latexify.py
pybamm/expression_tree/operations/serialise.py
pybamm/expression_tree/operations/unpack_symbols.py
pybamm/expression_tree/printing/__init__.py
pybamm/expression_tree/printing/print_name.py
pybamm/expression_tree/printing/sympy_overrides.py
pybamm-25.10.1.dist-info/METADATA
pybamm-25.10.1.dist-info/WHEEL
pybamm-25.10.1.dist-info/entry_points.txt
pybamm-25.10.1.dist-info/licenses/LICENSE.txt
pybamm-25.10.1.dist-info/RECORD
